{"advanced_config.md":"CUVG5Ghq","advanced_custom_js_css.md":"DwdHlJOX","advanced_custom_js_css_old.md":"-MDANTtb","advanced_landscap.md":"D7PpPyfO","advanced_mysql_redis.md":"CfOnLB9z","advanced_use_reverse_proxy.md":"DaZQ9OXq","browser_extension_index.md":"D_Cx1GND","browser_extension_update_log.md":"Vr3FBPf2","faq_faq.md":"BqPE8VzY","index.md":"CZhR2Dav","introduce_author_groups.md":"hg4yjQGG","introduce_demo_site.md":"DcGYgnoH","introduce_donate.md":"DMgpFWLP","introduce_project.md":"im3p-jgm","openapi_v1_apis.md":"BbqzjsK2","openapi_v1_error_code.md":"DioY6BIr","other_icon_wallpaper_recommend_sites.md":"CrjmPeZI","update_update_beta.md":"Bdgeq5IL","update_update_log.md":"CR-vLOkX","usage_backend_static_compilation.md":"DXxE8-8u","usage_compile.md":"SAWALD8c","usage_custom_footer.md":"CkyEj7ri","usage_public_visit.md":"DESEHLn8","usage_quick_deploy.md":"0KONE3ut","usage_reset_password.md":"CQeMUWEP","zh_cn_advanced_config.md":"Ctca07uc","zh_cn_advanced_custom_js_css.md":"tXLi4f_8","zh_cn_advanced_custom_js_css_old.md":"DExtXEjd","zh_cn_advanced_landscap.md":"C3DRNeSb","zh_cn_advanced_mysql_redis.md":"DcfIelhv","zh_cn_advanced_use_reverse_proxy.md":"5LK9fTXt","zh_cn_browser_extension_index.md":"D3KjPfqM","zh_cn_browser_extension_update_log.md":"buzpfsqE","zh_cn_faq_faq.md":"CISggG_M","zh_cn_index.md":"BMMScxNO","zh_cn_introduce_author_groups.md":"lYjr9ptB","zh_cn_introduce_demo_site.md":"_0zZClLv","zh_cn_introduce_donate.md":"DwpYq93X","zh_cn_introduce_project.md":"BolfvOM3","zh_cn_openapi_v1_apis.md":"CBzFqEuV","zh_cn_openapi_v1_error_code.md":"Ch2H3oB6","zh_cn_other_icon_wallpaper_recommend_sites.md":"DUhMFFzN","zh_cn_update_update_beta.md":"CHEUDnDc","zh_cn_update_update_log.md":"BLjvzIMr","zh_cn_usage_backend_static_compilation.md":"DJ_cd2LZ","zh_cn_usage_compile.md":"ASj__ltZ","zh_cn_usage_custom_footer.md":"CkRsE8u3","zh_cn_usage_public_visit.md":"zJeTo7Vc","zh_cn_usage_quick_deploy.md":"76Nesqq2","zh_cn_usage_reset_password.md":"CGELrAH7"}
